tvidentify/__init__.py
tvidentify/batch_identifier.py
tvidentify/episode_identifier.py
tvidentify/file_renamer.py
tvidentify/imagemaker.py
tvidentify/pgsreader.py
tvidentify/subtitle_extractor.py
tvidentify/subtitle_handlers.py
tvidentify/utils.py
tvidentify/vobsubreader.py
tvidentify-0.1.5.dist-info/METADATA
tvidentify-0.1.5.dist-info/WHEEL
tvidentify-0.1.5.dist-info/entry_points.txt
tvidentify-0.1.5.dist-info/top_level.txt
tvidentify-0.1.5.dist-info/RECORD
