Metadata-Version: 2.4
Name: tvidentify
Version: 0.1.5
Summary: A tool to identify TV episodes from video files and rename them to match Plex naming conventions.
License-Expression: MIT
Project-URL: Homepage, https://github.com/ram-nat/tvidentify/
Project-URL: Repository, https://github.com/ram-nat/tvidentify.git
Keywords: tv,episode,identifier,plex,renamer,subtitle,ocr
Requires-Python: >=3.8
Requires-Dist: opencv-python-headless
Requires-Dist: pytesseract
Requires-Dist: openai
Requires-Dist: google-genai
Provides-Extra: dev
Requires-Dist: pytest; extra == "dev"
Requires-Dist: pytest-mock; extra == "dev"
